python_mojepanstwo/__init__.py
python_mojepanstwo/exceptions.py
python_mojepanstwo/python_mojepanstwo.py
python_mojepanstwo/utils.py
python_mojepanstwo-0.1.0.dist-info/DESCRIPTION.rst
python_mojepanstwo-0.1.0.dist-info/METADATA
python_mojepanstwo-0.1.0.dist-info/RECORD
python_mojepanstwo-0.1.0.dist-info/WHEEL
python_mojepanstwo-0.1.0.dist-info/metadata.json
python_mojepanstwo-0.1.0.dist-info/top_level.txt
