Metadata-Version: 2.0
Name: python-mojepanstwo
Version: 0.1.0
Summary: A Python client for mojePaństwo API.
Home-page: https://github.com/ad-m/python_mojepanstwo
Author: Adam Dobrawy
Author-email: naczelnik@jawnosc.tk
License: MIT license
Keywords: python_mojepanstwo
Platform: UNKNOWN
Classifier: Development Status :: 2 - Pre-Alpha
Classifier: Intended Audience :: Developers
Classifier: License :: OSI Approved :: MIT License
Classifier: Natural Language :: English
Classifier: Programming Language :: Python :: 2
Classifier: Programming Language :: Python :: 2.6
Classifier: Programming Language :: Python :: 2.7
Classifier: Programming Language :: Python :: 3
Classifier: Programming Language :: Python :: 3.3
Classifier: Programming Language :: Python :: 3.4
Classifier: Programming Language :: Python :: 3.5
Requires-Dist: requests
